audapter/__init__.py
audapter/domain/model.py
audapter/driver/__init__.py
audapter/driver/filter_driver.py
audapter/driver/sound_driver.py
audapter/helper/__init__.py
audapter/helper/filter.py
audapter/helper/impulse_response.py
audapter/helper/load_config.py
audapter/helper/types.py
audapter/interface/__init__.py
audapter/interface/driver/filter_driver.py
audapter/interface/driver/sound_driver.py
audapter/settings.toml
audapter-0.1.1.dist-info/LICENSE
audapter-0.1.1.dist-info/WHEEL
audapter-0.1.1.dist-info/METADATA
audapter-0.1.1.dist-info/RECORD
